[
    {
        "Name": "Cơm Tấm Phúc Lộc Thọ",
        "Opentime": "7:00",
        "Closetime": "21:00",
        "Space": 0,
        "Rate": 4,
        "Image": "https://cdn.beptruong.edu.vn/wp-content/uploads/2018/06/cach-uop-thit-nuong-com-tam.jpg",
        "address": {
            "fullAddress": "",
            "long": 10.7333968,
            "lat": 106.62573549999999
        }
    },
    {
        "Name": "Hủ Tiếu Nam Vang Thành Đạt",
        "Opentime": "7:00",
        "Closetime": "21:00",
        "Space": 0,
        "Rate": 4.6,
        "Image": "https://images.foody.vn/res/g97/966927/prof/s640x400/foody-upload-api-foody-mobile-310-191210153650.jpg",
        "address": {
            "fullAddress": "",
            "long": 10.765537122680971,
            "lat": 106.695441898181
        }
    },
    {
        "Name": "Phở Hùng",
        "Opentime": "7:00",
        "Closetime": "21:00",
        "Space": 0,
        "Rate": 3.5,
        "Image": "https://media.foody.vn/res/g1/1362/prof/s/foody-mobile-pho-hung-nguyen-trai-986-635810420871508422.jpg",
        "address": {
            "fullAddress": "",
            "long": 10.765537122680971,
            "lat": 106.695441898181
        }
    },
    {
        "Name": "Dominos Pizza",
        "Opentime": "9:00",
        "Closetime": "21:00",
        "Space": 0,
        "Rate": 5,
        "Image": "https://stc.shopiness.vn/deal/2021/04/27/3/6/0/a/1619495579843_540.png",
        "address": {
            "fullAddress": "",
            "long": 10.765537122680971,
            "lat": 106.695441898181
        }
    },
    {
        "Name": "Kirin Sushi - Sushi - Hoàng Ngân",
        "Opentime": "9:00",
        "Closetime": "21:00",
        "Space": 0,
        "Rate": 3,
        "Image": "https://salt.tikicdn.com/ts/product/8b/65/4c/d2f241e42cc13564e639b060f370bd6d.png",
        "address": {
            "fullAddress": "",
            "long": 10.765537122680971,
            "lat": 106.695441898181
        }
    }
]